elope/elope.py
elope/__init__.py
elope-0.1.dist-info/RECORD
elope-0.1.dist-info/metadata.json
elope-0.1.dist-info/DESCRIPTION.rst
elope-0.1.dist-info/WHEEL
elope-0.1.dist-info/METADATA
elope-0.1.dist-info/top_level.txt
