Metadata-Version: 2.0
Name: elope
Version: 0.1
Summary: Trying to bring the elvis operator to python
Home-page: https://gitlab.com/andrewgy8/elope
Author: Andrew Graham-Yooll
Author-email: andrewgy8@gmail.com
License: MIT
Keywords: elvis operator javascript conditional safe-navigation-operator
Platform: UNKNOWN
Classifier: License :: OSI Approved :: MIT License
Classifier: Programming Language :: Python :: 3.6
